AUTHORS
HISTORY.rst
LICENSE
MANIFEST.in
README.rst
setup.py
djangoprojectrecipe/__init__.py
djangoprojectrecipe/fcgi.py
djangoprojectrecipe/manage.py
djangoprojectrecipe/recipe.py
djangoprojectrecipe/test.py
djangoprojectrecipe/wsgi.py
djangoprojectrecipe.egg-info/PKG-INFO
djangoprojectrecipe.egg-info/SOURCES.txt
djangoprojectrecipe.egg-info/dependency_links.txt
djangoprojectrecipe.egg-info/entry_points.txt
djangoprojectrecipe.egg-info/not-zip-safe
djangoprojectrecipe.egg-info/requires.txt
djangoprojectrecipe.egg-info/top_level.txt