Metadata-Version: 1.0
Name: djangoprojectrecipe
Version: 1.1.2
Summary: simple buildout recipe for django projects
Home-page: http://github.com/stefanfoulis/djangoprojectrecipe
Author: Stefan Foulis
Author-email: stefan.foulis@gmail.com
License: BSD
Platform: UNKNOWN
Classifier: Framework :: Buildout
Classifier: Framework :: Django
Classifier: Topic :: Software Development :: Build Tools
Classifier: Development Status :: 5 - Production/Stable
Classifier: License :: OSI Approved :: BSD License
